promptheus/__init__.py
promptheus/_provider_data.py
promptheus/ascii_art.py
promptheus/cli.py
promptheus/commands/__init__.py
promptheus/commands/auth.py
promptheus/commands/completion.py
promptheus/commands/providers.py
promptheus/commands/template.py
promptheus/commands/web.py
promptheus/completions/__init__.py
promptheus/completions/completion.py
promptheus/completions/templates/bash.bash
promptheus/completions/templates/zsh.zsh
promptheus/config.py
promptheus/constants.py
promptheus/core.py
promptheus/exceptions.py
promptheus/history.py
promptheus/io_context.py
promptheus/logging_config.py
promptheus/main.py
promptheus/mcp_server.py
promptheus/models_dev_service.py
promptheus/prompts.py
promptheus/providers.json
promptheus/providers.py
promptheus/question_prompter.py
promptheus/repl/__init__.py
promptheus/repl/commands.py
promptheus/repl/completer.py
promptheus/repl/history_view.py
promptheus/repl/session.py
promptheus/repl.py
promptheus/telemetry.py
promptheus/telemetry_summary.py
promptheus/utils.py
promptheus/web/__init__.py
promptheus/web/api/__init__.py
promptheus/web/api/history_router.py
promptheus/web/api/prompt_router.py
promptheus/web/api/providers_router.py
promptheus/web/api/questions_router.py
promptheus/web/api/settings_router.py
promptheus/web/server.py
promptheus/web/static/android-chrome-192x192.png
promptheus/web/static/android-chrome-512x512.png
promptheus/web/static/app.js
promptheus/web/static/app.js.bak
promptheus/web/static/apple-touch-icon.png
promptheus/web/static/favicon-16x16.png
promptheus/web/static/favicon-32x32.png
promptheus/web/static/favicon.ico
promptheus/web/static/index.html
promptheus/web/static/site.webmanifest
promptheus/web/static/styles.css
promptheus/web/static/web-ui-guide.html
promptheus-0.3.2.dist-info/METADATA
promptheus-0.3.2.dist-info/WHEEL
promptheus-0.3.2.dist-info/entry_points.txt
promptheus-0.3.2.dist-info/licenses/LICENSE
promptheus-0.3.2.dist-info/RECORD
