Metadata-Version: 2.4
Name: promptheus
Version: 0.3.2
Summary: AI-powered prompt engineering CLI tool
License: MIT
License-File: LICENSE
Keywords: ai,prompt-engineering,cli,gemini,llm
Author: Promptheus Contributors
Requires-Python: >=3.10,<4.0
Classifier: Development Status :: 3 - Alpha
Classifier: Intended Audience :: Developers
Classifier: License :: OSI Approved :: MIT License
Classifier: Programming Language :: Python :: 3
Classifier: Programming Language :: Python :: 3.10
Classifier: Programming Language :: Python :: 3.11
Classifier: Programming Language :: Python :: 3.12
Classifier: Programming Language :: Python :: 3.13
Classifier: Programming Language :: Python :: 3.14
Classifier: Programming Language :: Python :: 3.8
Classifier: Programming Language :: Python :: 3.9
Classifier: Topic :: Software Development :: Libraries :: Python Modules
Requires-Dist: aiohttp (>=3.9.0,<4.0.0)
Requires-Dist: anthropic (>=0.70.0,<0.71.0)
Requires-Dist: fastapi (>=0.115.0,<0.116.0)
Requires-Dist: filelock (>=3.20.0,<4.0.0)
Requires-Dist: google-genai (>=1.49.0,<2.0.0)
Requires-Dist: mcp (>=1.0.0,<2.0.0)
Requires-Dist: openai (>=1.51.0,<2.0.0)
Requires-Dist: prompt_toolkit (>=3.0.52,<4.0.0)
Requires-Dist: pyperclip (>=1.11.0,<2.0.0)
Requires-Dist: python-dotenv (>=1.2.0,<2.0.0)
Requires-Dist: questionary (>=2.1.0,<3.0.0)
Requires-Dist: rich (>=14.0.0,<15.0.0)
Requires-Dist: uvicorn[standard] (>=0.24.0,<0.25.0)
Project-URL: Homepage, https://github.com/abhichandra21/Promptheus
Project-URL: Repository, https://github.com/abhichandra21/Promptheus
